mcrand/__init__.py
mcrand/integrate.py
mcrand/randgen.py
mcrand-0.0.2.dist-info/LICENSE
mcrand-0.0.2.dist-info/METADATA
mcrand-0.0.2.dist-info/WHEEL
mcrand-0.0.2.dist-info/top_level.txt
mcrand-0.0.2.dist-info/RECORD
