Metadata-Version: 2.1
Name: mcrand
Version: 0.0.2
Summary: MCRand is a library of Monte Carlo methods implementing multidimensional integration                  and non-uniform random number generation.
Home-page: https://github.com/Physics-Simulations/MCRand
Author: Physics Simulations
Author-email: apuntsdefisica@gmail.com
License: UNKNOWN
Platform: UNKNOWN
Classifier: Programming Language :: Python :: 3
Classifier: License :: OSI Approved :: Apache Software License
Classifier: Operating System :: OS Independent
Classifier: Topic :: Scientific/Engineering :: Mathematics
Requires-Python: >=3.6
Requires-Dist: numpy (>=1.18)
Requires-Dist: scipy (>=1.5)
